AUTHORS
CHANGES
LICENSE
MANIFEST.in
Makefile
TODO
ez_setup.py
pygmentize
setup.cfg
setup.py
docs/generate.py
docs/pygmentize.1
docs/src/api.txt
docs/src/authors.txt
docs/src/changelog.txt
docs/src/cmdline.txt
docs/src/filterdevelopment.txt
docs/src/filters.txt
docs/src/formatterdevelopment.txt
docs/src/formatters.txt
docs/src/index.txt
docs/src/installation.txt
docs/src/integrate.txt
docs/src/lexerdevelopment.txt
docs/src/lexers.txt
docs/src/moinmoin.txt
docs/src/plugins.txt
docs/src/quickstart.txt
docs/src/rstdirective.txt
docs/src/styles.txt
docs/src/tokens.txt
docs/src/unicode.txt
external/markdown-processor.py
external/moin-parser.py
external/pygments.bashcomp
external/rst-directive-old.py
external/rst-directive.py
pygments/__init__.py
pygments/cmdline.py
pygments/console.py
pygments/filter.py
pygments/formatter.py
pygments/lexer.py
pygments/plugin.py
pygments/scanner.py
pygments/style.py
pygments/token.py
pygments/unistring.py
pygments/util.py
pygments/filters/__init__.py
pygments/formatters/__init__.py
pygments/formatters/_mapping.py
pygments/formatters/bbcode.py
pygments/formatters/html.py
pygments/formatters/img.py
pygments/formatters/latex.py
pygments/formatters/other.py
pygments/formatters/rtf.py
pygments/formatters/svg.py
pygments/formatters/terminal.py
pygments/formatters/terminal256.py
pygments/lexers/__init__.py
pygments/lexers/_asybuiltins.py
pygments/lexers/_clbuiltins.py
pygments/lexers/_luabuiltins.py
pygments/lexers/_mapping.py
pygments/lexers/_phpbuiltins.py
pygments/lexers/_vimbuiltins.py
pygments/lexers/agile.py
pygments/lexers/asm.py
pygments/lexers/compiled.py
pygments/lexers/dotnet.py
pygments/lexers/functional.py
pygments/lexers/hdl.py
pygments/lexers/math.py
pygments/lexers/other.py
pygments/lexers/parsers.py
pygments/lexers/special.py
pygments/lexers/templates.py
pygments/lexers/text.py
pygments/lexers/web.py
pygments/styles/__init__.py
pygments/styles/autumn.py
pygments/styles/borland.py
pygments/styles/bw.py
pygments/styles/colorful.py
pygments_hack.egg-info/PKG-INFO
pygments_hack.egg-info/SOURCES.txt
pygments_hack.egg-info/dependency_links.txt
pygments_hack.egg-info/entry_points.txt
pygments_hack.egg-info/not-zip-safe
pygments_hack.egg-info/top_level.txt
