Metadata-Version: 1.0
Name: pygments-hack
Version: 0.2
Summary: Pygments is a syntax highlighting package written in Python. This package is a modified version of pygments targetting code lines highlighting.
Home-page: http://pygments.org/
Author: UNKNOWN
Author-email: UNKNOWN
License: BSD License
Keywords: syntax highlighting
Platform: any
Classifier: License :: OSI Approved :: BSD License
Classifier: Intended Audience :: Developers
Classifier: Intended Audience :: End Users/Desktop
Classifier: Intended Audience :: System Administrators
Classifier: Development Status :: 5 - Production/Stable
Classifier: Programming Language :: Python
Classifier: Programming Language :: Python :: 2
Classifier: Programming Language :: Python :: 3
Classifier: Operating System :: OS Independent
